pymakeplots/__init__.py
pymakeplots/pymakeplots.py
pymakeplots/sauron_colormap.py
pymakeplots-0.2.5.dist-info/LICENSE.md
pymakeplots-0.2.5.dist-info/METADATA
pymakeplots-0.2.5.dist-info/WHEEL
pymakeplots-0.2.5.dist-info/top_level.txt
pymakeplots-0.2.5.dist-info/zip-safe
pymakeplots-0.2.5.dist-info/RECORD
