Metadata-Version: 2.1
Name: pymakeplots
Version: 0.2.5
Home-page: https://github.com/TimothyADavis/pymakeplots
Author: Timothy A. Davis
Author-email: DavisT@cardiff.ac.uk
License: MIT
Classifier: Development Status :: 4 - Beta
Classifier: License :: OSI Approved :: MIT License
Classifier: Programming Language :: Python :: 3
Classifier: Operating System :: OS Independent
License-File: LICENSE.md
Requires-Dist: numpy
Requires-Dist: matplotlib >3.3.1
Requires-Dist: scipy >=1.14.0
Requires-Dist: astropy
Requires-Dist: spectral-cube
Requires-Dist: radio-beam
Requires-Dist: pafit
